geneticpy/__init__.py
geneticpy/optimize_function.py
geneticpy/parameter_set.py
geneticpy/population.py
geneticpy/distributions/__init__.py
geneticpy/distributions/distribution_base.py
geneticpy-2.0.0.dist-info/METADATA
geneticpy-2.0.0.dist-info/WHEEL
geneticpy-2.0.0.dist-info/licenses/LICENSE
geneticpy-2.0.0.dist-info/RECORD
