Metadata-Version: 2.4
Name: geneticpy
Version: 2.0.0
Summary: GeneticPy is an optimizer that uses a genetic algorithm to quickly search through custom parameter spaces for optimal solutions.
Project-URL: Homepage, https://github.com/geneticpy/geneticpy
Project-URL: Documentation, https://geneticpy.readthedocs.io
Project-URL: Bug Tracker, https://github.com/geneticpy/geneticpy/issues
Project-URL: Source Code, https://github.com/geneticpy/geneticpy
Author-email: Brandon Schabell <brandonschabell@gmail.com>
License-Expression: MIT
License-File: LICENSE
Keywords: ai,artificial intelligence,data science,genetic algorithm,machine learning,optimization
Classifier: Development Status :: 5 - Production/Stable
Classifier: Intended Audience :: Developers
Classifier: Intended Audience :: Science/Research
Classifier: License :: OSI Approved :: MIT License
Classifier: Programming Language :: Python :: 3
Classifier: Programming Language :: Python :: 3.10
Classifier: Programming Language :: Python :: 3.11
Classifier: Programming Language :: Python :: 3.12
Classifier: Programming Language :: Python :: 3.13
Classifier: Programming Language :: Python :: 3.14
Classifier: Topic :: Scientific/Engineering
Classifier: Topic :: Software Development
Classifier: Topic :: Utilities
Requires-Python: >=3.10
Requires-Dist: numpy
Requires-Dist: tqdm
